{
  "backgrounds": {
    "1.jpg": ["Gojo Satoru chilling like a boss in the night sky", 1000],
    "2.jpg": ["Goku, in mastered Ultra Instinct, flexing cosmic swag", 5000],
    "3.jpg": ["Goku, in Ultra Instinct, lookin' fancy", 4000],
    "4.jpg": ["Broly, the beefiest Super Saiyan, breaking limits (and necks)", 6000],
    "5.jpg": ["Asta, going 'no magic? No problem!' with anti-magic", 2500],
    "6.jpg": ["Sasuke Uchiha, emo king of the Uchihas", 2000],
    "7.jpg": ["Sasuke rocking Akatsuki drip", 3000],
    "8.jpg": ["Giyu Tomiyoka, stoic water dude chilling", 3500],
    "9.jpg": ["Sasuke vs. Naruto: The OG Frenemy Saga", 1500],
    "10.jpg": ["GTR—because everyone dreams, but few can afford", 700],
    "11.jpg": ["Serena Mons, the logo MVP", 500],
    "12.jpg": ["My Neighbor Totoro: Fluffy legend", 2000],
    "13.jpg": ["Shanks: the cool red-haired pirate uncle", 3500],
    "14.jpg": ["Yuji Itadori, nap goals on a train", 2500],
    "15.jpg": ["Vegeta, prince of pride and salty rivalries", 4500],
    "16.jpg": ["Miles Morales, Spider-Man but with swag", 1500],
    "17.jpg": ["Sung Jin-Woo, solo leveling like a pro", 3000],
    "18.jpg": ["Gojo vs. Sukuna: 'Nah, I'd win' vibes", 3500],
    "19.jpg": ["Goku Black, Super Saiyan Rose (extra fancy)", 2800],
    "20.jpg": ["Itachi: 'You're already trapped in my Genjutsu, bro'", 700]
  },
  "cards": {
    "1.jpg": ["Sasuke joins Akatsuki: Now 100% edgier!", 800],
    "2.jpg": ["Goku goes Super Saiyan: Instant goosebumps", 1200],
    "3.jpg": ["Gojo Satoru showing off Purple Hollow: Too OP", 700],
    "4.jpg": ["Senku about to invent something unnecessary but amazing", 950],
    "5.jpg": ["Seishiro Nagi from Blue Lock: Ball is life", 1000],
    "6.jpg": ["Bachira Meguru doing his goofy magic again", 999],
    "7.jpg": ["Kaguya-sama plotting world domination (probably)", 2400],
    "8.jpg": ["Esdeath: Still lethal, still thicc", 2800],
    "9.jpg": ["Byakuya Kuchiki unleashing sakura petal fury", 1100],
    "10.jpg": ["Killua Zoldyck: Electric assassin kid vibes", 800],
    "11.jpg": ["Sukuna: King of curses and cocky smirks", 1800],
    "12.jpg": ["Saitama: 'One punch, no problem!'", 4500],
    "13.jpg": ["Nami-swan: Budgeting queen and navigator extraordinaire", 3700],
    "14.jpg": ["Ace: The fire boy we still miss", 4000],
    "15.jpg": ["Zoro, pirate hunter and directionally challenged", 3800],
    "16.jpg": ["Luffy, future Pirate King and chaos magnet", 5999],
    "17.jpg": ["Sakamoto: 'Ever heard of me? Of course you have.'", 1400],
    "18.jpg": ["Killua: Assassin mode but make it cute", 2800],
    "19.jpg": ["God Usopp: Living the dream (sorta)", 3900],
    "20.jpg": ["Kurapika: Chains and revenge on his mind", 1800]
  }
}
